{"authorDailyContributionsMap":{"Calvin-GH":[{"date":"2026-02-04T00:00:00","commitResults":[{"hash":"0a982da001bec3c9167d72ce9b53eb828c273549","isMergeCommit":false,"messageTitle":"Level-0: Rename chatbot to Timer, greet and exit","messageBody":"","fileTypesAndContributionMap":{"java":{"insertions":10,"deletions":10}}},{"hash":"04c951d6be518939f833f1d254d9cb819167552d","isMergeCommit":false,"messageTitle":"Level 1-1: Echo and exit on bye","messageBody":"","tags":["Level1-1"],"fileTypesAndContributionMap":{"java":{"insertions":24,"deletions":3}}},{"hash":"a9a2ff278bf1cc371d971de1e41b296499f31c76","isMergeCommit":false,"messageTitle":"Level1-2: Add and list tasks","messageBody":"","tags":["Level1-2"],"fileTypesAndContributionMap":{"java":{"insertions":28,"deletions":4}}},{"hash":"d637cbddcaf111c62a2ae7f885c542c626ed2836","isMergeCommit":false,"messageTitle":"Level1-3: Mark and unmark tasks","messageBody":"","tags":["Level1-3"],"fileTypesAndContributionMap":{"java":{"insertions":53,"deletions":1}}},{"hash":"fec55869ed4cbc9619bf9e606e3f592f6fb2e447","isMergeCommit":false,"messageTitle":"Level1-4: Todo, Deadline, Event","messageBody":"","tags":["Level1-4"],"fileTypesAndContributionMap":{"java":{"insertions":185,"deletions":21}}}]},{"date":"2026-02-05T00:00:00","commitResults":[{"hash":"49eaf051254e74639246a7ff6e59826c69c9469b","isMergeCommit":false,"messageTitle":"A-CodeQuality: Extract Task, Todo, Deadline, and Event into separate classes for better readability","messageBody":"","tags":["A-CodeQuality"],"fileTypesAndContributionMap":{"java":{"insertions":140,"deletions":151}}},{"hash":"d980c39c10a8fded6dc7c4769c055b5b0a17165e","isMergeCommit":false,"messageTitle":"Remoced repeated Hello message","messageBody":"","fileTypesAndContributionMap":{"java":{"insertions":0,"deletions":3}}},{"hash":"d6994289d6ee3d83168e9c313021eb2889f7b253","isMergeCommit":false,"messageTitle":"Revert \"Remoced repeated Hello message\"","messageBody":"This reverts commit d980c39c10a8fded6dc7c4769c055b5b0a17165e.\n","fileTypesAndContributionMap":{"java":{"insertions":3,"deletions":0}}},{"hash":"86409e5762ddf5ae515f8359f2e3df0bb49e53e9","isMergeCommit":false,"messageTitle":"Customised welcome message","messageBody":"","fileTypesAndContributionMap":{"java":{"insertions":3,"deletions":7}}}]}]},"authorFileTypeContributionMap":{"Calvin-GH":{"java":256,"md":0,"fxml":0,"sh":0,"bat":0,"gradle":0,"txt":0}},"authorContributionVariance":{"Calvin-GH":6938.066},"authorDisplayNameMap":{"Calvin-GH":"CS2113-T11-3 CALV..UANG"}}
