{"authorDailyContributionsMap":{"Jas0n-yxy":[{"date":"2026-02-04T00:00:00","commitResults":[{"hash":"10f3af340ebf2ae7c43790349e208631aefd99ca","isMergeCommit":false,"messageTitle":"first commit","messageBody":"","tags":["Level-4"],"fileTypesAndContributionMap":{"java":{"insertions":120,"deletions":10},"bat":{"insertions":1,"deletions":1},"md":{"insertions":3,"deletions":3}}}]},{"date":"2026-02-09T00:00:00","commitResults":[{"hash":"b5354a94d1fc7b6bb0ea7eea6a9bfcbf5f105995","isMergeCommit":false,"messageTitle":"Stop tracking EXPECTED-UNIX.TXT and update test files","messageBody":"","tags":["Level-5"],"fileTypesAndContributionMap":{"txt":{"insertions":6,"deletions":0},"java":{"insertions":267,"deletions":73},"sh":{"insertions":1,"deletions":1}}}]}]},"authorFileTypeContributionMap":{"Jas0n-yxy":{"java":314,"md":3,"fxml":0,"sh":1,"bat":1,"gradle":0,"txt":6}},"authorContributionVariance":{"Jas0n-yxy":4148.965},"authorDisplayNameMap":{"Jas0n-yxy":"CS2113-W13-3 YAN ..NGYU"}}
