[{"path":"src/main/java/Gojo.java","fileType":"java","lines":[{"lineNumber":1,"author":{"gitId":"1cecream03"},"content":"import java.util.Scanner;","lastModifiedDate":"2026-01-30T03:55:15","isFullCredit":false},{"lineNumber":2,"author":{"gitId":"1cecream03"},"content":"","lastModifiedDate":"2026-01-30T03:55:15","isFullCredit":false},{"lineNumber":3,"author":{"gitId":"1cecream03"},"content":"public class Gojo {","lastModifiedDate":"2026-01-29T02:18:25","isFullCredit":false},{"lineNumber":4,"author":{"gitId":"1cecream03"},"content":"","lastModifiedDate":"2026-01-29T02:18:25","isFullCredit":false},{"lineNumber":5,"author":{"gitId":"1cecream03"},"content":"    public static void main(String[] args) {","lastModifiedDate":"2026-01-29T02:18:25","isFullCredit":false},{"lineNumber":6,"author":{"gitId":"1cecream03"},"content":"        String name \u003d \"Gojo\";","lastModifiedDate":"2026-01-29T02:18:25","isFullCredit":false},{"lineNumber":7,"author":{"gitId":"1cecream03"},"content":"        Scanner in \u003d new Scanner(System.in);","lastModifiedDate":"2026-01-30T03:55:15","isFullCredit":false},{"lineNumber":8,"author":{"gitId":"1cecream03"},"content":"","lastModifiedDate":"2026-01-29T02:18:25","isFullCredit":false},{"lineNumber":9,"author":{"gitId":"1cecream03"},"content":"        Task[] tasks \u003d new Task[100];","lastModifiedDate":"2026-01-30T14:44:32","isFullCredit":false},{"lineNumber":10,"author":{"gitId":"1cecream03"},"content":"        int taskCount \u003d 0;","lastModifiedDate":"2026-01-30T03:59:21","isFullCredit":false},{"lineNumber":11,"author":{"gitId":"1cecream03"},"content":"","lastModifiedDate":"2026-01-30T03:59:21","isFullCredit":false},{"lineNumber":12,"author":{"gitId":"1cecream03"},"content":"        printLine();","lastModifiedDate":"2026-01-29T02:18:25","isFullCredit":false},{"lineNumber":13,"author":{"gitId":"1cecream03"},"content":"        System.out.println(\"Throughout heaven and earth, I alone am the honored one.\");","lastModifiedDate":"2026-01-29T02:25:59","isFullCredit":false},{"lineNumber":14,"author":{"gitId":"1cecream03"},"content":"        System.out.println(\"I\u0027m \" + name + \". Ask me anything.\");","lastModifiedDate":"2026-01-29T02:25:59","isFullCredit":false},{"lineNumber":15,"author":{"gitId":"1cecream03"},"content":"        printLine();","lastModifiedDate":"2026-01-29T02:18:25","isFullCredit":false},{"lineNumber":16,"author":{"gitId":"1cecream03"},"content":"","lastModifiedDate":"2026-01-29T02:18:25","isFullCredit":false},{"lineNumber":17,"author":{"gitId":"1cecream03"},"content":"        String command;","lastModifiedDate":"2026-01-30T03:55:15","isFullCredit":false},{"lineNumber":18,"author":{"gitId":"1cecream03"},"content":"        while (true) {","lastModifiedDate":"2026-01-30T03:55:15","isFullCredit":false},{"lineNumber":19,"author":{"gitId":"1cecream03"},"content":"            command \u003d in.nextLine();","lastModifiedDate":"2026-01-30T03:55:15","isFullCredit":false},{"lineNumber":20,"author":{"gitId":"1cecream03"},"content":"","lastModifiedDate":"2026-01-30T03:59:21","isFullCredit":false},{"lineNumber":21,"author":{"gitId":"1cecream03"},"content":"            // Case 1: Exit","lastModifiedDate":"2026-01-30T03:59:21","isFullCredit":false},{"lineNumber":22,"author":{"gitId":"1cecream03"},"content":"            if (command.equals(\"bye\")) {","lastModifiedDate":"2026-01-30T03:55:15","isFullCredit":false},{"lineNumber":23,"author":{"gitId":"1cecream03"},"content":"                printLine();","lastModifiedDate":"2026-01-30T03:59:21","isFullCredit":false},{"lineNumber":24,"author":{"gitId":"1cecream03"},"content":"                System.out.println(\"Bye. Don\u0027t get weak while I\u0027m gone.\");","lastModifiedDate":"2026-01-30T03:59:21","isFullCredit":false},{"lineNumber":25,"author":{"gitId":"1cecream03"},"content":"                printLine();","lastModifiedDate":"2026-01-30T03:59:21","isFullCredit":false},{"lineNumber":26,"author":{"gitId":"1cecream03"},"content":"                break;","lastModifiedDate":"2026-01-30T03:55:15","isFullCredit":false},{"lineNumber":27,"author":{"gitId":"1cecream03"},"content":"            }","lastModifiedDate":"2026-01-30T03:55:15","isFullCredit":false},{"lineNumber":28,"author":{"gitId":"1cecream03"},"content":"            // Case 2: List all tasks","lastModifiedDate":"2026-01-30T03:59:21","isFullCredit":false},{"lineNumber":29,"author":{"gitId":"1cecream03"},"content":"            else if (command.equals(\"list\")) {","lastModifiedDate":"2026-01-30T03:59:21","isFullCredit":false},{"lineNumber":30,"author":{"gitId":"1cecream03"},"content":"                printLine();","lastModifiedDate":"2026-01-30T03:55:15","isFullCredit":false},{"lineNumber":31,"author":{"gitId":"1cecream03"},"content":"                System.out.println(\"Here are the tasks in your list. Try to keep up:\");","lastModifiedDate":"2026-01-30T03:59:21","isFullCredit":false},{"lineNumber":32,"author":{"gitId":"1cecream03"},"content":"                for (int i \u003d 0; i \u003c taskCount; i++) {","lastModifiedDate":"2026-01-30T03:59:21","isFullCredit":false},{"lineNumber":33,"author":{"gitId":"1cecream03"},"content":"                    System.out.println((i + 1) + \".\" + tasks[i]);","lastModifiedDate":"2026-01-30T03:59:21","isFullCredit":false},{"lineNumber":34,"author":{"gitId":"1cecream03"},"content":"                }","lastModifiedDate":"2026-01-30T03:59:21","isFullCredit":false},{"lineNumber":35,"author":{"gitId":"1cecream03"},"content":"                printLine();","lastModifiedDate":"2026-01-30T03:55:15","isFullCredit":false},{"lineNumber":36,"author":{"gitId":"1cecream03"},"content":"            }","lastModifiedDate":"2026-01-30T03:55:15","isFullCredit":false},{"lineNumber":37,"author":{"gitId":"1cecream03"},"content":"            // Case 3: Add a new task (Default)","lastModifiedDate":"2026-01-30T03:59:21","isFullCredit":false},{"lineNumber":38,"author":{"gitId":"1cecream03"},"content":"            else if (command.startsWith(\"mark \")) {","lastModifiedDate":"2026-01-30T14:44:32","isFullCredit":false},{"lineNumber":39,"author":{"gitId":"1cecream03"},"content":"                // Extract the number (e.g., \"2\") and convert to integer","lastModifiedDate":"2026-01-30T14:44:32","isFullCredit":false},{"lineNumber":40,"author":{"gitId":"1cecream03"},"content":"                int taskNumber \u003d Integer.parseInt(command.substring(5));","lastModifiedDate":"2026-01-30T14:44:32","isFullCredit":false},{"lineNumber":41,"author":{"gitId":"1cecream03"},"content":"                int index \u003d taskNumber - 1; // Adjust for 0-based array index","lastModifiedDate":"2026-01-30T14:44:32","isFullCredit":false},{"lineNumber":42,"author":{"gitId":"1cecream03"},"content":"","lastModifiedDate":"2026-01-30T14:44:32","isFullCredit":false},{"lineNumber":43,"author":{"gitId":"1cecream03"},"content":"                tasks[index].markAsDone();","lastModifiedDate":"2026-01-30T14:44:32","isFullCredit":false},{"lineNumber":44,"author":{"gitId":"1cecream03"},"content":"","lastModifiedDate":"2026-01-30T14:44:32","isFullCredit":false},{"lineNumber":45,"author":{"gitId":"1cecream03"},"content":"                printLine();","lastModifiedDate":"2026-01-30T14:44:32","isFullCredit":false},{"lineNumber":46,"author":{"gitId":"1cecream03"},"content":"                System.out.println(\"Good. I\u0027ve marked this task as done:\");","lastModifiedDate":"2026-01-30T14:44:32","isFullCredit":false},{"lineNumber":47,"author":{"gitId":"1cecream03"},"content":"                System.out.println(\"  \" + tasks[index]);","lastModifiedDate":"2026-01-30T14:44:32","isFullCredit":false},{"lineNumber":48,"author":{"gitId":"1cecream03"},"content":"                printLine();","lastModifiedDate":"2026-01-30T14:44:32","isFullCredit":false},{"lineNumber":49,"author":{"gitId":"1cecream03"},"content":"            }","lastModifiedDate":"2026-01-30T14:44:32","isFullCredit":false},{"lineNumber":50,"author":{"gitId":"1cecream03"},"content":"            else if (command.startsWith(\"unmark \")) {","lastModifiedDate":"2026-01-30T14:44:32","isFullCredit":false},{"lineNumber":51,"author":{"gitId":"1cecream03"},"content":"                int taskNumber \u003d Integer.parseInt(command.substring(7));","lastModifiedDate":"2026-01-30T14:44:32","isFullCredit":false},{"lineNumber":52,"author":{"gitId":"1cecream03"},"content":"                int index \u003d taskNumber - 1;","lastModifiedDate":"2026-01-30T14:44:32","isFullCredit":false},{"lineNumber":53,"author":{"gitId":"1cecream03"},"content":"","lastModifiedDate":"2026-01-30T14:44:32","isFullCredit":false},{"lineNumber":54,"author":{"gitId":"1cecream03"},"content":"                tasks[index].markAsUndone();","lastModifiedDate":"2026-01-30T14:44:32","isFullCredit":false},{"lineNumber":55,"author":{"gitId":"1cecream03"},"content":"","lastModifiedDate":"2026-01-30T14:44:32","isFullCredit":false},{"lineNumber":56,"author":{"gitId":"1cecream03"},"content":"                printLine();","lastModifiedDate":"2026-01-30T14:44:32","isFullCredit":false},{"lineNumber":57,"author":{"gitId":"1cecream03"},"content":"                System.out.println(\"Okay, I\u0027ve marked this task as not done:\");","lastModifiedDate":"2026-01-30T14:44:32","isFullCredit":false},{"lineNumber":58,"author":{"gitId":"1cecream03"},"content":"                System.out.println(\"  \" + tasks[index]);","lastModifiedDate":"2026-01-30T14:44:32","isFullCredit":false},{"lineNumber":59,"author":{"gitId":"1cecream03"},"content":"                printLine();","lastModifiedDate":"2026-01-30T14:44:32","isFullCredit":false},{"lineNumber":60,"author":{"gitId":"1cecream03"},"content":"            }","lastModifiedDate":"2026-01-30T14:44:32","isFullCredit":false},{"lineNumber":61,"author":{"gitId":"1cecream03"},"content":"            else {","lastModifiedDate":"2026-01-30T03:59:21","isFullCredit":false},{"lineNumber":62,"author":{"gitId":"1cecream03"},"content":"                // CHANGE 5: Create a new Task object instead of just a string","lastModifiedDate":"2026-01-30T14:44:32","isFullCredit":false},{"lineNumber":63,"author":{"gitId":"1cecream03"},"content":"                tasks[taskCount] \u003d new Task(command);","lastModifiedDate":"2026-01-30T14:44:32","isFullCredit":false},{"lineNumber":64,"author":{"gitId":"1cecream03"},"content":"                taskCount++;","lastModifiedDate":"2026-01-30T03:59:21","isFullCredit":false},{"lineNumber":65,"author":{"gitId":"1cecream03"},"content":"","lastModifiedDate":"2026-01-30T03:55:15","isFullCredit":false},{"lineNumber":66,"author":{"gitId":"1cecream03"},"content":"                printLine();","lastModifiedDate":"2026-01-29T02:18:25","isFullCredit":false},{"lineNumber":67,"author":{"gitId":"1cecream03"},"content":"                System.out.println(\"added: \" + command);","lastModifiedDate":"2026-01-30T03:59:21","isFullCredit":false},{"lineNumber":68,"author":{"gitId":"1cecream03"},"content":"                printLine();","lastModifiedDate":"2026-01-30T03:59:21","isFullCredit":false},{"lineNumber":69,"author":{"gitId":"1cecream03"},"content":"            }","lastModifiedDate":"2026-01-30T03:59:21","isFullCredit":false},{"lineNumber":70,"author":{"gitId":"1cecream03"},"content":"        }","lastModifiedDate":"2026-01-30T03:59:21","isFullCredit":false},{"lineNumber":71,"author":{"gitId":"1cecream03"},"content":"    }","lastModifiedDate":"2026-01-29T02:18:25","isFullCredit":false},{"lineNumber":72,"author":{"gitId":"1cecream03"},"content":"","lastModifiedDate":"2026-01-29T02:18:25","isFullCredit":false},{"lineNumber":73,"author":{"gitId":"1cecream03"},"content":"    public static void printLine() {","lastModifiedDate":"2026-01-29T02:18:25","isFullCredit":false},{"lineNumber":74,"author":{"gitId":"1cecream03"},"content":"        System.out.println(\"____________________________________________________________\");","lastModifiedDate":"2026-01-29T02:18:25","isFullCredit":false},{"lineNumber":75,"author":{"gitId":"1cecream03"},"content":"    }","lastModifiedDate":"2026-01-29T02:18:25","isFullCredit":false},{"lineNumber":76,"author":{"gitId":"1cecream03"},"content":"}","lastModifiedDate":"2026-01-29T02:18:25","isFullCredit":false}],"authorContributionMap":{"1cecream03":76}},{"path":"src/main/java/Task.java","fileType":"java","lines":[{"lineNumber":1,"author":{"gitId":"1cecream03"},"content":"public class Task {","lastModifiedDate":"2026-01-30T14:44:32","isFullCredit":false},{"lineNumber":2,"author":{"gitId":"1cecream03"},"content":"    protected String description;","lastModifiedDate":"2026-01-30T14:44:32","isFullCredit":false},{"lineNumber":3,"author":{"gitId":"1cecream03"},"content":"    protected boolean isDone;","lastModifiedDate":"2026-01-30T14:44:32","isFullCredit":false},{"lineNumber":4,"author":{"gitId":"1cecream03"},"content":"","lastModifiedDate":"2026-01-30T14:44:32","isFullCredit":false},{"lineNumber":5,"author":{"gitId":"1cecream03"},"content":"    public Task(String description) {","lastModifiedDate":"2026-01-30T14:44:32","isFullCredit":false},{"lineNumber":6,"author":{"gitId":"1cecream03"},"content":"        this.description \u003d description;","lastModifiedDate":"2026-01-30T14:44:32","isFullCredit":false},{"lineNumber":7,"author":{"gitId":"1cecream03"},"content":"        this.isDone \u003d false;","lastModifiedDate":"2026-01-30T14:44:32","isFullCredit":false},{"lineNumber":8,"author":{"gitId":"1cecream03"},"content":"    }","lastModifiedDate":"2026-01-30T14:44:32","isFullCredit":false},{"lineNumber":9,"author":{"gitId":"1cecream03"},"content":"","lastModifiedDate":"2026-01-30T14:44:32","isFullCredit":false},{"lineNumber":10,"author":{"gitId":"1cecream03"},"content":"    public String getStatusIcon() {","lastModifiedDate":"2026-01-30T14:44:32","isFullCredit":false},{"lineNumber":11,"author":{"gitId":"1cecream03"},"content":"        return (isDone ? \"X\" : \" \");","lastModifiedDate":"2026-01-30T14:44:32","isFullCredit":false},{"lineNumber":12,"author":{"gitId":"1cecream03"},"content":"    }","lastModifiedDate":"2026-01-30T14:44:32","isFullCredit":false},{"lineNumber":13,"author":{"gitId":"1cecream03"},"content":"","lastModifiedDate":"2026-01-30T14:44:32","isFullCredit":false},{"lineNumber":14,"author":{"gitId":"1cecream03"},"content":"    public void markAsDone() {","lastModifiedDate":"2026-01-30T14:44:32","isFullCredit":false},{"lineNumber":15,"author":{"gitId":"1cecream03"},"content":"        this.isDone \u003d true;","lastModifiedDate":"2026-01-30T14:44:32","isFullCredit":false},{"lineNumber":16,"author":{"gitId":"1cecream03"},"content":"    }","lastModifiedDate":"2026-01-30T14:44:32","isFullCredit":false},{"lineNumber":17,"author":{"gitId":"1cecream03"},"content":"","lastModifiedDate":"2026-01-30T14:44:32","isFullCredit":false},{"lineNumber":18,"author":{"gitId":"1cecream03"},"content":"    public void markAsUndone() {","lastModifiedDate":"2026-01-30T14:44:32","isFullCredit":false},{"lineNumber":19,"author":{"gitId":"1cecream03"},"content":"        this.isDone \u003d false;","lastModifiedDate":"2026-01-30T14:44:32","isFullCredit":false},{"lineNumber":20,"author":{"gitId":"1cecream03"},"content":"    }","lastModifiedDate":"2026-01-30T14:44:32","isFullCredit":false},{"lineNumber":21,"author":{"gitId":"1cecream03"},"content":"","lastModifiedDate":"2026-01-30T14:44:32","isFullCredit":false},{"lineNumber":22,"author":{"gitId":"1cecream03"},"content":"    public String toString() {","lastModifiedDate":"2026-01-30T14:44:32","isFullCredit":false},{"lineNumber":23,"author":{"gitId":"1cecream03"},"content":"        return \"[\" + getStatusIcon() + \"] \" + description;","lastModifiedDate":"2026-01-30T14:44:32","isFullCredit":false},{"lineNumber":24,"author":{"gitId":"1cecream03"},"content":"    }","lastModifiedDate":"2026-01-30T14:44:32","isFullCredit":false},{"lineNumber":25,"author":{"gitId":"1cecream03"},"content":"}","lastModifiedDate":"2026-01-30T14:44:32","isFullCredit":false}],"authorContributionMap":{"1cecream03":25}}]
