{"authorDailyContributionsMap":{"bryanyeo3125":[{"date":"2026-02-02T00:00:00","commitResults":[{"hash":"99223c81beedf973c4300971646f0ab90a195934","isMergeCommit":false,"messageTitle":"initial commit","messageBody":"","fileTypesAndContributionMap":{"java":{"insertions":51,"deletions":10}}},{"hash":"1738055a86d0e620376f3dd525567de41d9bc72b","isMergeCommit":false,"messageTitle":"Week 3 Tasks","messageBody":"","fileTypesAndContributionMap":{"java":{"insertions":167,"deletions":51}}}]}]},"authorFileTypeContributionMap":{"bryanyeo3125":{"java":167,"md":0,"fxml":0,"sh":0,"bat":0,"gradle":0,"txt":0}},"authorContributionVariance":{"bryanyeo3125":2989.0945},"authorDisplayNameMap":{"bryanyeo3125":"CS2113-F14-2 YEO ..RYAN"}}
